setup.cfg
setup.py
bd_tokenize/__init__.py
bd_tokenize/bn_tokenizer.py
bd_tokenize/bn_word_tokens.py
bd_tokenize.egg-info/PKG-INFO
bd_tokenize.egg-info/SOURCES.txt
bd_tokenize.egg-info/dependency_links.txt
bd_tokenize.egg-info/top_level.txt