Metadata-Version: 1.0
Name: bd-tokenize
Version: 0.0.1
Summary: Bangla Language Tests
Home-page: UNKNOWN
Author: Aditta Das
Author-email: UNKNOWN
License: MIT
Platform: UNKNOWN
